openpyxl-stubs/METADATA.toml
openpyxl-stubs/__init__.pyi
openpyxl-stubs/_constants.pyi
openpyxl-stubs/py.typed
openpyxl-stubs/cell/__init__.pyi
openpyxl-stubs/cell/_writer.pyi
openpyxl-stubs/cell/cell.pyi
openpyxl-stubs/cell/read_only.pyi
openpyxl-stubs/cell/rich_text.pyi
openpyxl-stubs/cell/text.pyi
openpyxl-stubs/chart/_3d.pyi
openpyxl-stubs/chart/__init__.pyi
openpyxl-stubs/chart/_chart.pyi
openpyxl-stubs/chart/area_chart.pyi
openpyxl-stubs/chart/axis.pyi
openpyxl-stubs/chart/bar_chart.pyi
openpyxl-stubs/chart/bubble_chart.pyi
openpyxl-stubs/chart/chartspace.pyi
openpyxl-stubs/chart/data_source.pyi
openpyxl-stubs/chart/descriptors.pyi
openpyxl-stubs/chart/error_bar.pyi
openpyxl-stubs/chart/label.pyi
openpyxl-stubs/chart/layout.pyi
openpyxl-stubs/chart/legend.pyi
openpyxl-stubs/chart/line_chart.pyi
openpyxl-stubs/chart/marker.pyi
openpyxl-stubs/chart/picture.pyi
openpyxl-stubs/chart/pie_chart.pyi
openpyxl-stubs/chart/pivot.pyi
openpyxl-stubs/chart/plotarea.pyi
openpyxl-stubs/chart/print_settings.pyi
openpyxl-stubs/chart/radar_chart.pyi
openpyxl-stubs/chart/reader.pyi
openpyxl-stubs/chart/reference.pyi
openpyxl-stubs/chart/scatter_chart.pyi
openpyxl-stubs/chart/series.pyi
openpyxl-stubs/chart/series_factory.pyi
openpyxl-stubs/chart/shapes.pyi
openpyxl-stubs/chart/stock_chart.pyi
openpyxl-stubs/chart/surface_chart.pyi
openpyxl-stubs/chart/text.pyi
openpyxl-stubs/chart/title.pyi
openpyxl-stubs/chart/trendline.pyi
openpyxl-stubs/chart/updown_bars.pyi
openpyxl-stubs/chartsheet/__init__.pyi
openpyxl-stubs/chartsheet/chartsheet.pyi
openpyxl-stubs/chartsheet/custom.pyi
openpyxl-stubs/chartsheet/properties.pyi
openpyxl-stubs/chartsheet/protection.pyi
openpyxl-stubs/chartsheet/publish.pyi
openpyxl-stubs/chartsheet/relation.pyi
openpyxl-stubs/chartsheet/views.pyi
openpyxl-stubs/comments/__init__.pyi
openpyxl-stubs/comments/author.pyi
openpyxl-stubs/comments/comment_sheet.pyi
openpyxl-stubs/comments/comments.pyi
openpyxl-stubs/comments/shape_writer.pyi
types_openpyxl-3.1.5.20250914.dist-info/licenses/LICENSE
types_openpyxl-3.1.5.20250914.dist-info/METADATA
types_openpyxl-3.1.5.20250914.dist-info/WHEEL
types_openpyxl-3.1.5.20250914.dist-info/top_level.txt
types_openpyxl-3.1.5.20250914.dist-info/RECORD
